LICENSE
README.md
pyproject.toml
setup.py
src/ibm_vpc_img_inst/__init__.py
src/ibm_vpc_img_inst/config_builder.py
src/ibm_vpc_img_inst/constants.py
src/ibm_vpc_img_inst/defaults.yaml
src/ibm_vpc_img_inst/main.py
src/ibm_vpc_img_inst/utils.py
src/ibm_vpc_img_inst.egg-info/PKG-INFO
src/ibm_vpc_img_inst.egg-info/SOURCES.txt
src/ibm_vpc_img_inst.egg-info/dependency_links.txt
src/ibm_vpc_img_inst.egg-info/entry_points.txt
src/ibm_vpc_img_inst.egg-info/requires.txt
src/ibm_vpc_img_inst.egg-info/top_level.txt
src/ibm_vpc_img_inst/bin/__init__.py
src/ibm_vpc_img_inst/bin/ibm_vpc_img_inst.py
src/ibm_vpc_img_inst/config_modules/__init__.py
src/ibm_vpc_img_inst/config_modules/apikey_config.py
src/ibm_vpc_img_inst/config_modules/delete_resources.py
src/ibm_vpc_img_inst/config_modules/endpoint_config.py
src/ibm_vpc_img_inst/config_modules/image_config.py
src/ibm_vpc_img_inst/config_modules/image_create.py
src/ibm_vpc_img_inst/config_modules/install_feature.py
src/ibm_vpc_img_inst/config_modules/ip_config.py
src/ibm_vpc_img_inst/config_modules/ssh_config.py
src/ibm_vpc_img_inst/config_modules/vpc_config.py
src/ibm_vpc_img_inst/config_modules/vsi_config.py
src/ibm_vpc_img_inst/installation_scripts/cuda/install_cuda_rhel.sh
src/ibm_vpc_img_inst/installation_scripts/cuda/install_cuda_ubuntu.sh
src/ibm_vpc_img_inst/installation_scripts/docker/install_docker_rhel.sh
src/ibm_vpc_img_inst/installation_scripts/docker/install_docker_ubuntu.sh