Metadata-Version: 2.1
Name: ibm-vpc-img-inst
Version: 1.0.0b3
Summary: Produces IBM-VPC custom image in users account with an installed tool of their choosing
Home-page: https://github.com/IBM-Cloud/ibm-vpc-img-inst
Author:  Omer J Cohen
Author-email: cohen.j.omer@gmail.com
Requires-Python: >=3.6
License-File: LICENSE
